uniquebible/htmlResources/images/exlbl_largeHD_1/BL1.png
uniquebible/htmlResources/images/exlbl_largeHD_1/BL10.png
uniquebible/htmlResources/images/exlbl_largeHD_1/BL100.png
uniquebible/htmlResources/images/exlbl_largeHD_1/BL101.png
uniquebible/htmlResources/images/exlbl_largeHD_1/BL102.png
uniquebible/htmlResources/images/exlbl_largeHD_1/BL103.png
uniquebible/htmlResources/images/exlbl_largeHD_1/BL105.png
uniquebible/htmlResources/images/exlbl_largeHD_1/BL106.png
uniquebible/htmlResources/images/exlbl_largeHD_1/BL107.png
uniquebible/htmlResources/images/exlbl_largeHD_1/BL108.png
uniquebible/htmlResources/images/exlbl_largeHD_1/BL109.png
uniquebible/htmlResources/images/exlbl_largeHD_1/BL110.png
uniquebible/htmlResources/images/exlbl_largeHD_1/BL111.png
uniquebible/htmlResources/images/exlbl_largeHD_1/BL113.png
uniquebible/htmlResources/images/exlbl_largeHD_1/BL114.png
uniquebible/htmlResources/images/exlbl_largeHD_1/BL115.png
uniquebible/htmlResources/images/exlbl_largeHD_1/BL117.png
uniquebible/htmlResources/images/exlbl_largeHD_1/BL118.png
uniquebible/htmlResources/images/exlbl_largeHD_1/BL119.png
uniquebible/htmlResources/images/exlbl_largeHD_1/BL12.png
uniquebible/htmlResources/images/exlbl_largeHD_1/BL120.png
uniquebible/htmlResources/images/exlbl_largeHD_1/BL121.png
uniquebible/htmlResources/images/exlbl_largeHD_1/BL122.png
uniquebible/htmlResources/images/exlbl_largeHD_1/BL123.png
uniquebible/htmlResources/images/exlbl_largeHD_1/BL124.png
uniquebible/htmlResources/images/exlbl_largeHD_1/BL125.png
uniquebible/htmlResources/images/exlbl_largeHD_1/BL126.png
uniquebible/htmlResources/images/exlbl_largeHD_1/BL128.png
uniquebible/htmlResources/images/exlbl_largeHD_1/BL129.png
uniquebible/htmlResources/images/exlbl_largeHD_1/BL13.png
uniquebible/htmlResources/images/exlbl_largeHD_1/BL130.png
uniquebible/htmlResources/images/exlbl_largeHD_1/BL131.png
uniquebible/htmlResources/images/exlbl_largeHD_1/BL132.png
uniquebible_maps_3-0.0.3.dist-info/LICENSE
uniquebible_maps_3-0.0.3.dist-info/METADATA
uniquebible_maps_3-0.0.3.dist-info/WHEEL
uniquebible_maps_3-0.0.3.dist-info/top_level.txt
uniquebible_maps_3-0.0.3.dist-info/RECORD
